report_generator/__init__.py
report_generator/__main__.py
report_generator_plavist-0.1.0.dist-info/METADATA
report_generator_plavist-0.1.0.dist-info/WHEEL
report_generator_plavist-0.1.0.dist-info/top_level.txt
report_generator_plavist-0.1.0.dist-info/RECORD
