Metadata-Version: 2.1
Name: report_generator_plavist
Version: 0.1.0
Author: Plavist Games
Requires-Python: >=3.12
Requires-Dist: pandas
